dataset_builder/__init__.py
dataset_builder/__main__.py
dataset_builder/ezg.py
dataset_builder/radolan.py
dataset_builder/run.py
dataset_builder/reducers/__init__.py
dataset_builder/reducers/radolan.py
dataset_builder/reducers/station.py
dataset_builder-0.2.0.dist-info/LICENSE
dataset_builder-0.2.0.dist-info/METADATA
dataset_builder-0.2.0.dist-info/WHEEL
dataset_builder-0.2.0.dist-info/entry_points.txt
dataset_builder-0.2.0.dist-info/top_level.txt
dataset_builder-0.2.0.dist-info/RECORD
