Metadata-Version: 2.1
Name: dataset-builder
Version: 0.2.0
Summary: Dataset builder for CAMELS-DE dataset
Author: Mirko Mälicke
Author-email: mirko@hydrocode.de
License: GNU General Public License v3.0
Platform: UNKNOWN
License-File: LICENSE
Requires-Dist: rasterio
Requires-Dist: shapely
Requires-Dist: geopandas
Requires-Dist: fiona
Requires-Dist: wetterdienst
Requires-Dist: pyproj
Requires-Dist: python-dateutil
Requires-Dist: fire
